pyequalizer/Filter.py
pyequalizer/__init__.py
pyequalizer/__version__.py
pyequalizer/utils.py
pyequalizer-0.1.0.dist-info/LICENSE
pyequalizer-0.1.0.dist-info/METADATA
pyequalizer-0.1.0.dist-info/WHEEL
pyequalizer-0.1.0.dist-info/top_level.txt
pyequalizer-0.1.0.dist-info/RECORD
