Metadata-Version: 2.1
Name: pyequalizer
Version: 0.1.0
Summary: A time domain equalizer which is mainly implemented by scipy 
Home-page: https://github.com/me/myproject
Author: Awesome Soul
Author-email: tw40210@gmail.com
License: MIT
Platform: UNKNOWN
Classifier: License :: OSI Approved :: MIT License
Classifier: Programming Language :: Python
Classifier: Programming Language :: Python :: 3
Classifier: Programming Language :: Python :: 3.6
Classifier: Programming Language :: Python :: Implementation :: CPython
Classifier: Programming Language :: Python :: Implementation :: PyPy
Requires-Python: >=3.6.0
